jellfyin_openapi_client-1.0.0.dist-info/licenses/LICENSE.md
openapi_client/__init__.py
openapi_client/api_client.py
openapi_client/api_response.py
openapi_client/configuration.py
openapi_client/exceptions.py
openapi_client/py.typed
openapi_client/rest.py
openapi_client/api/__init__.py
openapi_client/api/activity_log_api.py
openapi_client/api/api_key_api.py
openapi_client/api/artists_api.py
openapi_client/api/audio_api.py
openapi_client/api/backup_api.py
openapi_client/api/branding_api.py
openapi_client/api/channels_api.py
openapi_client/api/client_log_api.py
openapi_client/api/collection_api.py
openapi_client/api/configuration_api.py
openapi_client/api/dashboard_api.py
openapi_client/api/devices_api.py
openapi_client/api/display_preferences_api.py
openapi_client/api/dynamic_hls_api.py
openapi_client/api/environment_api.py
openapi_client/api/filter_api.py
openapi_client/api/genres_api.py
openapi_client/api/hls_segment_api.py
openapi_client/api/image_api.py
openapi_client/api/instant_mix_api.py
openapi_client/api/item_lookup_api.py
openapi_client/api/item_refresh_api.py
openapi_client/api/item_update_api.py
openapi_client/api/items_api.py
openapi_client/api/library_api.py
openapi_client/api/library_structure_api.py
openapi_client/api/live_tv_api.py
openapi_client/api/localization_api.py
openapi_client/api/lyrics_api.py
openapi_client/api/media_info_api.py
openapi_client/api/media_segments_api.py
openapi_client/api/movies_api.py
openapi_client/api/music_genres_api.py
openapi_client/api/package_api.py
openapi_client/api/persons_api.py
openapi_client/api/playlists_api.py
openapi_client/api/playstate_api.py
openapi_client/api/plugins_api.py
openapi_client/api/quick_connect_api.py
openapi_client/api/remote_image_api.py
openapi_client/api/scheduled_tasks_api.py
openapi_client/api/search_api.py
openapi_client/api/session_api.py
openapi_client/api/startup_api.py
openapi_client/api/studios_api.py
openapi_client/api/subtitle_api.py
openapi_client/api/suggestions_api.py
openapi_client/api/sync_play_api.py
jellfyin_openapi_client-1.0.0.dist-info/METADATA
jellfyin_openapi_client-1.0.0.dist-info/WHEEL
jellfyin_openapi_client-1.0.0.dist-info/top_level.txt
jellfyin_openapi_client-1.0.0.dist-info/RECORD
