Metadata-Version: 2.4
Name: jellfyin_openapi_client
Version: 1.0.0
Summary: Jellyfin API
Home-page: 
Author: OpenAPI Generator community
Author-email: OpenAPI Generator Community <team@openapitools.org>
License: MIT License
Project-URL: Repository, https://github.com/Thundernerd/jellyfin-openapi-client
Keywords: OpenAPI,OpenAPI-Generator,Jellyfin API
Requires-Python: >=3.9
License-File: LICENSE.md
Requires-Dist: urllib3<3.0.0,>=2.1.0
Requires-Dist: python-dateutil>=2.8.2
Requires-Dist: pydantic>=2
Requires-Dist: typing-extensions>=4.7.1
Dynamic: author
Dynamic: license-file
